fw_gear_testing/__init__.py
fw_gear_testing/decorators.py
fw_gear_testing/files.py
fw_gear_testing/gears.py
fw_gear_testing/hierarchy.py
fw_gear_testing/sdk.py
fw_gear_testing/utils.py
fw_gear_testing-0.2.4.dist-info/LICENSE
fw_gear_testing-0.2.4.dist-info/WHEEL
fw_gear_testing-0.2.4.dist-info/METADATA
fw_gear_testing-0.2.4.dist-info/RECORD
